pyrecard/__init__.py
pyrecard/__version__.py
pyrecard/decorators.py
pyrecard/exceptions.py
pyrecard/subscription/__init__.py
pyrecard/subscription/coupon.py
pyrecard/subscription/customer.py
pyrecard/subscription/payment.py
pyrecard/subscription/plan.py
pyrecard/subscription/subscription.py
pyrecard/subscription/webhook.py
pyrecard/test/__init__.py
pyrecard/test/mock.py
pyrecard/utils/__init__.py
pyrecard/utils/factory.py
pyrecard/utils/pyrequest.py
tests/__init__.py
tests/factory_tests.py
tests/subscription_tests.py
pyrecard-1.0.0.dist-info/LICENSE
pyrecard-1.0.0.dist-info/METADATA
pyrecard-1.0.0.dist-info/WHEEL
pyrecard-1.0.0.dist-info/top_level.txt
pyrecard-1.0.0.dist-info/RECORD
