Metadata-Version: 2.1
Name: pyrecard
Version: 1.0.0
Summary: A Python lib for brazilian Wirecard payment gateway.
Home-page: https://github.com/DiegoMagg/pyrecard
Author: Diego Magalhães
Author-email: dmlmagal@gmail.com
License: UNKNOWN
Platform: UNKNOWN
Classifier: Programming Language :: Python :: 3
Classifier: License :: OSI Approved :: MIT License
Classifier: Operating System :: OS Independent
Requires-Python: >=3.6
Requires-Dist: requests
